{
  "fill" : {
    "linear-gradient" : [
      "display-p3:0.99268,0.99121,0.32812,1.00000",
      "display-p3:0.90223,0.90065,0.18452,1.00000"
    ],
    "orientation" : {
      "start" : {
        "x" : 0.5,
        "y" : 1
      },
      "stop" : {
        "x" : 0.5,
        "y" : 0.3
      }
    }
  },
  "groups" : [
    {
      "blur-material" : null,
      "layers" : [
        {
          "glass" : true,
          "image-name" : "Progetto senza titolo 3.svg",
          "name" : "Progetto senza titolo 3"
        }
      ],
      "lighting" : "individual",
      "shadow" : {
        "kind" : "neutral",
        "opacity" : 0.5
      },
      "translucency" : {
        "enabled" : true,
        "value" : 0.5
      }
    },
    {
      "layers" : [
        {
          "image-name" : "Progetto senza titolo.svg",
          "name" : "Progetto senza titolo",
          "position" : {
            "scale" : 1,
            "translation-in-points" : [
              0,
              0
            ]
          }
        }
      ],
      "shadow" : {
        "kind" : "neutral",
        "opacity" : 0.5
      },
      "translucency" : {
        "enabled" : true,
        "value" : 0.5
      }
    }
  ],
  "supported-platforms" : {
    "circles" : [
      "watchOS"
    ],
    "squares" : "shared"
  }
}